parsevasp/__init__.py
parsevasp/base.py
parsevasp/chgcar.py
parsevasp/constants.py
parsevasp/doscar.py
parsevasp/eigenval.py
parsevasp/incar.py
parsevasp/incar.yml
parsevasp/kpoints.py
parsevasp/outcar.py
parsevasp/poscar.py
parsevasp/potcar.py
parsevasp/stream.py
parsevasp/stream.yml
parsevasp/utils.py
parsevasp/vasprun.py
parsevasp-3.4.0.dist-info/licenses/LICENSE.txt
parsevasp-3.4.0.dist-info/WHEEL
parsevasp-3.4.0.dist-info/METADATA
parsevasp-3.4.0.dist-info/RECORD
