Metadata-Version: 2.4
Name: parsevasp
Version: 3.4.0
Summary: A general parser for VASP
Keywords: vasp,parser
Author-email: Espen Flage-Larsen	 <espen.flage-larsen@sigma2.no>
Requires-Python: >=3.9
Classifier: Programming Language :: Python
Classifier: Intended Audience :: Science/Research
Classifier: Natural Language :: English
Classifier: Development Status :: 5 - Production/Stable
Classifier: Environment :: Plugins
Classifier: Intended Audience :: Science/Research
Classifier: License :: OSI Approved :: MIT License
Classifier: Programming Language :: Python :: 3.9
Classifier: Programming Language :: Python :: 3.10
Classifier: Programming Language :: Python :: 3.11
Classifier: Programming Language :: Python :: 3.12
Classifier: Topic :: Scientific/Engineering :: Physics
Classifier: Topic :: Scientific/Engineering :: Chemistry
License-File: LICENSE.txt
Requires-Dist: numpy
Requires-Dist: lxml
Requires-Dist: pyyaml
Requires-Dist: pre-commit~=2.2 ; extra == "pre-commit"
Requires-Dist: pytest~=7.0 ; extra == "tests"
Requires-Dist: pytest-cov~=2.7,<2.11 ; extra == "tests"
Requires-Dist: coverage~=6.0 ; extra == "tests"
Project-URL: Source, https://github.com/aiida-vasp/parsevasp
Provides-Extra: pre-commit
Provides-Extra: tests
